lattereview/__init__.py
lattereview/_version.py
lattereview/agents/__init__.py
lattereview/agents/abstraction_reviewer.py
lattereview/agents/basic_reviewer.py
lattereview/agents/scoring_reviewer.py
lattereview/agents/title_abstract_reviewer.py
lattereview/providers/__init__.py
lattereview/providers/base_provider.py
lattereview/providers/google_provider.py
lattereview/providers/litellm_provider.py
lattereview/providers/ollama_provider.py
lattereview/providers/openai_provider.py
lattereview/utils/__init__.py
lattereview/utils/data_handler.py
lattereview/workflows/__init__.py
lattereview/workflows/review_workflow.py
lattereview-1.1.1.dist-info/licenses/LICENSE
lattereview-1.1.1.dist-info/METADATA
lattereview-1.1.1.dist-info/WHEEL
lattereview-1.1.1.dist-info/top_level.txt
lattereview-1.1.1.dist-info/RECORD
