Metadata-Version: 2.4
Name: lattereview
Version: 1.1.1
Summary: Add your description here
Home-page: https://github.com/PouriaRouzrokh/LatteReview
Author: Pouria Rouzrokh
Author-email: po.rouzrokh@gmail.com
Requires-Python: >=3.9
License-File: LICENSE
Requires-Dist: black>=24.10.0
Requires-Dist: build>=1.2.2.post1
Requires-Dist: flake8>=7.1.1
Requires-Dist: google>=3.0.0
Requires-Dist: google-genai>=1.15.0
Requires-Dist: ipykernel>=6.29.5
Requires-Dist: litellm>=1.55.2
Requires-Dist: matplotlib>=3.9.4
Requires-Dist: mkdocs>=1.6.1
Requires-Dist: mkdocs-gen-files>=0.5.0
Requires-Dist: mkdocs-literate-nav>=0.6.2
Requires-Dist: mkdocs-material>=9.6.12
Requires-Dist: mkdocstrings>=0.29.1
Requires-Dist: mkdocstrings-python>=1.16.10
Requires-Dist: nest-asyncio>=1.6.0
Requires-Dist: ollama>=0.4.4
Requires-Dist: openai>=1.57.4
Requires-Dist: opencv-python>=4.10.0.84
Requires-Dist: openpyxl>=3.1.5
Requires-Dist: pandas>=2.2.2
Requires-Dist: pillow>=11.0.0
Requires-Dist: pydantic>=2.10.3
Requires-Dist: python-dotenv>=1.0.1
Requires-Dist: setuptools>=80.0.0
Requires-Dist: tokencost>=0.1.17
Requires-Dist: tqdm>=4.67.1
Requires-Dist: twine>=6.1.0
Dynamic: author
Dynamic: author-email
Dynamic: home-page
Dynamic: license-file
Dynamic: requires-python
